setup.py
MySuperMath/__init__.py
MySuperMath/dome1.py
MySuperMath/dome2.py
MySupermath.egg-info/PKG-INFO
MySupermath.egg-info/SOURCES.txt
MySupermath.egg-info/dependency_links.txt
MySupermath.egg-info/top_level.txt