Metadata-Version: 2.1
Name: MySupermath
Version: 1.0
Summary: 这是第一个对外发布的模块，只用于进行测试
Author: huanglianqi
Author-email: 1062260387@qq.com
